[
  {
    "wId": "w1001",
    "wName": "Workout I",
    "wtId": "wt0001",
    "wDifficulty": 1,
    "qIds": ["q00006", "q00004", "q00003", "q00011"]
  },
  {
    "wId": "w1002",
    "wName": "Workout II",
    "wtId": "wt0001",
    "wDifficulty": 1,
    "qIds": ["q00011", "q00007", "q00006", "q00009"]
  },
  {
    "wId": "w1003",
    "wName": "Workout III",
    "wtId": "wt0001",
    "wDifficulty": 1,
    "qIds": ["q00004", "q00008", "q00010", "q00005"]
  },
  {
    "wId": "w1004",
    "wName": "Workout IV",
    "wtId": "wt0001",
    "wDifficulty": 1,
    "qIds": ["q00012", "q00002", "q00003", "q00001"]
  },
  {
    "wId": "w1005",
    "wName": "Workout V",
    "wtId": "wt0001",
    "wDifficulty": 1,
    "qIds": ["q00010", "q00003", "q00011", "q00012"]
  },
  {
    "wId": "w1006",
    "wName": "Workout VI",
    "wtId": "wt0001",
    "wDifficulty": 1,
    "qIds": ["q00004", "q00006", "q00012", "q00010"]
  },
  {
    "wId": "w1007",
    "wName": "Workout VII",
    "wtId": "wt0001",
    "wDifficulty": 1,
    "qIds": ["q00009", "q03001", "q00007", "q03002"]
  },
  {
    "wId": "w1008",
    "wName": "Workout VIII",
    "wtId": "wt0001",
    "wDifficulty": 1,
    "qIds": ["q00008", "q00001", "q00004", "q00003"]
  },
  {
    "wId": "w1009",
    "wName": "Workout IX",
    "wtId": "wt0001",
    "wDifficulty": 1,
    "qIds": ["q00005", "q00002", "q00010", "q00012"]
  },
  {
    "wId": "w1010",
    "wName": "Workout X",
    "wtId": "wt0001",
    "wDifficulty": 1,
    "qIds": ["q00007", "q00005", "q00001", "q00012"]
  },
  {
    "wId": "w1011",
    "wName": "Workout XI",
    "wtId": "wt0001",
    "wDifficulty": 1,
    "qIds": ["q00009", "q00008", "q00002", "q00003"]
  },
  {
    "wId": "w1012",
    "wName": "Workout XII",
    "wtId": "wt0001",
    "wDifficulty": 1,
    "qIds": ["q03001", "q00005", "q00011", "q00009"]
  },
  {
    "wId": "w1013",
    "wName": "Workout XIII",
    "wtId": "wt0001",
    "wDifficulty": 1,
    "qIds": ["q03002", "q00008", "q00006", "q00007"]
  },
  {
    "wId": "w1014",
    "wName": "Workout XIV",
    "wtId": "wt0001",
    "wDifficulty": 1,
    "qIds": ["q03001", "q00004", "q00005", "q00002"]
  },
  {
    "wId": "w1015",
    "wName": "Workout XV",
    "wtId": "wt0001",
    "wDifficulty": 1,
    "qIds": ["q03002", "q00010", "q00008", "q00001"]
  },
  {
    "wId": "w2001",
    "wName": "Workout I",
    "wtId": "wt0002",
    "wDifficulty": 2,
    "qIds": ["q00006", "q00004", "q00003", "q00011",
    "q02011", "q02002", "q01001", "q02010"]
  },
  {
    "wId": "w2002",
    "wName": "Workout II",
    "wtId": "wt0002",
    "wDifficulty": 2,
    "qIds": ["q00011", "q00007", "q00006", "q00009",
    "q02010", "q01017", "q02011", "q01014"]
  },
  {
    "wId": "w2003",
    "wName": "Workout III",
    "wtId": "wt0002",
    "wDifficulty": 2,
    "qIds": ["q00004", "q00008", "q00010", "q00005",
    "q02002", "q02001", "q02013", "q01003"]
  },
  {
    "wId": "w2004",
    "wName": "Workout IV",
    "wtId": "wt0002",
    "wDifficulty": 2,
    "qIds": ["q00012", "q00002", "q00003", "q00001",
    "q02012", "q01009", "q01001", "q01002"]
  },
  {
    "wId": "w2005",
    "wName": "Workout V",
    "wtId": "wt0002",
    "wDifficulty": 2,
    "qIds": ["q00010", "q00003", "q00011", "q00012",
    "q02013", "q01001", "q02010", "q02012"]
  },
  {
    "wId": "w2006",
    "wName": "Workout VI",
    "wtId": "wt0002",
    "wDifficulty": 2,
    "qIds": ["q00004", "q00006", "q00012", "q00010",
    "q02002", "q02011", "q02012", "q02013"]
  },
  {
    "wId": "w2007",
    "wName": "Workout VII",
    "wtId": "wt0002",
    "wDifficulty": 2,
    "qIds": ["q00009", "q03001", "q00007", "q03002",
    "q01014", "q03009", "q01017", "q03003"]
  },
  {
    "wId": "w2008",
    "wName": "Workout VIII",
    "wtId": "wt0002",
    "wDifficulty": 2,
    "qIds": ["q00008", "q00001", "q00004", "q00003",
    "q02001", "q01002", "q02002", "q01001"]
  },
  {
    "wId": "w2009",
    "wName": "Workout IX",
    "wtId": "wt0002",
    "wDifficulty": 2,
    "qIds": ["q00005", "q00002", "q00010", "q00012",
    "q01003", "q01009", "q02013", "q02012"]
  },
  {
    "wId": "w2010",
    "wName": "Workout X",
    "wtId": "wt0002",
    "wDifficulty": 2,
    "qIds": ["q00007", "q00005", "q00001", "q00012",
    "q01017", "q01003", "q01002", "q02012"]
  },
  {
    "wId": "w2011",
    "wName": "Workout XI",
    "wtId": "wt0002",
    "wDifficulty": 2,
    "qIds": ["q00009", "q00008", "q00002", "q00003",
    "q01014", "q02001", "q01009", "q01001"]
  },
  {
    "wId": "w2012",
    "wName": "Workout XII",
    "wtId": "wt0002",
    "wDifficulty": 2,
    "qIds": ["q03001", "q00005", "q00011", "q00009",
    "q03009", "q01003", "q02010", "q01014"]
  },
  {
    "wId": "w2013",
    "wName": "Workout XIII",
    "wtId": "wt0002",
    "wDifficulty": 2,
    "qIds": ["q03002", "q00008", "q00006", "q00007",
    "q03003", "q02001", "q02011", "q01017"]
  },
  {
    "wId": "w2014",
    "wName": "Workout XIV",
    "wtId": "wt0002",
    "wDifficulty": 2,
    "qIds": ["q03001", "q00004", "q00005", "q00002",
    "q03009", "q02002", "q01003", "q01009"]
  },
  {
    "wId": "w2015",
    "wName": "Workout XV",
    "wtId": "wt0002",
    "wDifficulty": 2,
    "qIds": ["q03002", "q00010", "q00008", "q00001",
    "q03003", "q02013", "q02001", "q01002"]
  },
  {
    "wId": "w3001",
    "wName": "Workout I",
    "wtId": "wt0003",
    "wDifficulty": 3,
    "qIds": ["q00006", "q00004", "q00003", "q00011",
    "q02011", "q02002", "q01001", "q02010",
    "q02004", "q02016", "q01004", "q01008"]
  },
  {
    "wId": "w3002",
    "wName": "Workout II",
    "wtId": "wt0003",
    "wDifficulty": 3,
    "qIds": ["q00011", "q00007", "q00006", "q00009",
    "q02010", "q01017", "q02011", "q01014",
    "q01008", "q01016", "q02004", "q01015"]
  },
  {
    "wId": "w3003",
    "wName": "Workout III",
    "wtId": "wt0003",
    "wDifficulty": 3,
    "qIds": ["q00004", "q00008", "q00010", "q00005",
    "q02002", "q02001", "q02013", "q01003",
    "q02016", "q01013", "q02015", "q02005"]
  },
  {
    "wId": "w3004",
    "wName": "Workout IV",
    "wtId": "wt0003",
    "wDifficulty": 3,
    "qIds": ["q00012", "q00002", "q00003", "q00001",
    "q02012", "q01009", "q01001", "q01002",
    "q02014", "q01010", "q01004", "q01005"]
  },
  {
    "wId": "w3005",
    "wName": "Workout V",
    "wtId": "wt0003",
    "wDifficulty": 3,
    "qIds": ["q00010", "q00003", "q00011", "q00012",
    "q02013", "q01001", "q02010", "q02012",
    "q02015", "q01004", "q01008", "q02014"]
  },
  {
    "wId": "w3006",
    "wName": "Workout VI",
    "wtId": "wt0003",
    "wDifficulty": 3,
    "qIds": ["q00004", "q00006", "q00012", "q00010",
    "q02002", "q02011", "q02012", "q02013",
    "q02016", "q02004", "q02014", "q02015"]
  },
  {
    "wId": "w3007",
    "wName": "Workout VII",
    "wtId": "wt0003",
    "wDifficulty": 3,
    "qIds": ["q00009", "q03001", "q00007", "q03002",
    "q01014", "q03009", "q01017", "q03003",
    "q01015", "q03004", "q01016", "q03005"]
  },
  {
    "wId": "w3008",
    "wName": "Workout VIII",
    "wtId": "wt0003",
    "wDifficulty": 3,
    "qIds": ["q00008", "q00001", "q00004", "q00003",
    "q02001", "q01002", "q02002", "q01001",
    "q01013", "q01005", "q02016", "q01004"]
  },
  {
    "wId": "w3009",
    "wName": "Workout IX",
    "wtId": "wt0003",
    "wDifficulty": 3,
    "qIds": ["q00005", "q00002", "q00010", "q00012",
    "q01003", "q01009", "q02013", "q02012",
    "q02005", "q01010", "q02015", "q02014"]
  },
  {
    "wId": "w3010",
    "wName": "Workout X",
    "wtId": "wt0003",
    "wDifficulty": 3,
    "qIds": ["q00007", "q00005", "q00001", "q00012",
    "q01017", "q01003", "q01002", "q02012",
    "q01016", "q02005", "q01005", "q02014"]
  },
  {
    "wId": "w3011",
    "wName": "Workout XI",
    "wtId": "wt0003",
    "wDifficulty": 3,
    "qIds": ["q00009", "q00008", "q00002", "q00003",
    "q01014", "q02001", "q01009", "q01001",
    "q01015", "q01013", "q01010", "q01004"]
  },
  {
    "wId": "w3012",
    "wName": "Workout XII",
    "wtId": "wt0003",
    "wDifficulty": 3,
    "qIds": ["q03001", "q00005", "q00011", "q00009",
    "q03009", "q01003", "q02010", "q01014",
    "q03004", "q02005", "q01008", "q01015"]
  },
  {
    "wId": "w3013",
    "wName": "Workout XIII",
    "wtId": "wt0003",
    "wDifficulty": 3,
    "qIds": ["q03002", "q00008", "q00006", "q00007",
    "q03003", "q02001", "q02011", "q01017",
    "q03005", "q01013", "q02004", "q01016"]
  },
  {
    "wId": "w3014",
    "wName": "Workout XIV",
    "wtId": "wt0003",
    "wDifficulty": 3,
    "qIds": ["q03001", "q00004", "q00005", "q00002",
    "q03009", "q02002", "q01003", "q01009",
    "q03004", "q02016", "q02005", "q01010"]
  },
  {
    "wId": "w3015",
    "wName": "Workout XV",
    "wtId": "wt0003",
    "wDifficulty": 3,
    "qIds": ["q03002", "q00010", "q00008", "q00001",
    "q03003", "q02013", "q02001", "q01002",
    "q03005", "q02015", "q01013", "q01005"]
  },




  {
    "wId": "w4001",
    "wName": "Workout I",
    "wtId": "wt0004",
    "wDifficulty": 4,
    "qIds": ["q00006", "q00004", "q00003", "q00011",
    "q02008", "q02011", "q02004", "q02016",
    "q02002", "q01008", "q02010", "q02007"]
  },
  {
    "wId": "w4002",
    "wName": "Workout II",
    "wtId": "wt0004",
    "wDifficulty": 4,
    "qIds": ["q00011", "q00007", "q00006", "q00009",
    "q01007", "q01017", "q02017", "q01016",
    "q01015", "q02008", "q01014", "q01006"]
  },
  {
    "wId": "w4003",
    "wName": "Workout III",
    "wtId": "wt0004",
    "wDifficulty": 4,
    "qIds": ["q00004", "q00008", "q00010", "q00005",
    "q02009", "q02001", "q02008", "q01013",
    "q02005", "q02007", "q01003", "q02006"]
  },
  {
    "wId": "w4004",
    "wName": "Workout IV",
    "wtId": "wt0004",
    "wDifficulty": 4,
    "qIds": ["q00012", "q00002", "q00003", "q00001",
    "q01011", "q01009", "q02003", "q01010",
    "q01005", "q02007", "q01002", "q01012"]
  },
  {
    "wId": "w4005",
    "wName": "Workout V",
    "wtId": "wt0004",
    "wDifficulty": 4,
    "qIds": ["q00010", "q00003", "q00011", "q00012",
    "q03008", "q01001", "q02017", "q01004",
    "q02014", "q02003", "q02012", "q03010"]
  },
  {
    "wId": "w4006",
    "wName": "Workout VI",
    "wtId": "wt0004",
    "wDifficulty": 4,
    "qIds": ["q00004", "q00006", "q00012", "q00010",
    "q02017", "q02002", "q02016", "q02004",
    "q02011", "q02015", "q02013", "q02003"]
  },
  {
    "wId": "w4007",
    "wName": "Workout VII",
    "wtId": "wt0004",
    "wDifficulty": 4,
    "qIds": ["q00009", "q03001", "q00007", "q03002",
    "q03006", "q03009", "q03004", "q01007",
    "q03005", "q01006", "q03003", "q03007"]
  },
  {
    "wId": "w4008",
    "wName": "Workout VIII",
    "wtId": "wt0004",
    "wDifficulty": 4,
    "qIds": ["q00008", "q00001", "q00004", "q00003",
    "q02009", "q01002", "q02007", "q01004",
    "q01013", "q01012", "q02002", "q03007"]
  },
  {
    "wId": "w4009",
    "wName": "Workout IX",
    "wtId": "wt0004",
    "wDifficulty": 4,
    "qIds": ["q00005", "q00002", "q00010", "q00012",
    "q02006", "q01009", "q02017", "q02014",
    "q02005", "q01011", "q02013", "q03006"]
  },
  {
    "wId": "w4010",
    "wName": "Workout X",
    "wtId": "wt0004",
    "wDifficulty": 4,
    "qIds": ["q00007", "q00005", "q00001", "q00012",
    "q01007", "q01003", "q01012", "q02014",
    "q01016", "q02006", "q01002", "q03006"]
  },
  {
    "wId": "w4011",
    "wName": "Workout XI",
    "wtId": "wt0004",
    "wDifficulty": 4,
    "qIds": ["q00009", "q00008", "q00002", "q00003",
    "q01006", "q02001", "q01011", "q01004",
    "q01015", "q02009", "q01009", "q03007"]
  },
  {
    "wId": "w4012",
    "wName": "Workout XII",
    "wtId": "wt0004",
    "wDifficulty": 4,
    "qIds": ["q03001", "q00005", "q00011", "q00009",
    "q03010", "q01003", "q02003", "q01015",
    "q03004", "q02006", "q02010", "q01006"]
  },
  {
    "wId": "w4013",
    "wName": "Workout XIII",
    "wtId": "wt0004",
    "wDifficulty": 4,
    "qIds": ["q03002", "q00008", "q00006", "q00007",
    "q03008", "q02001", "q02008", "q01016",
    "q03005", "q02009", "q02011", "q01007"]
  },
  {
    "wId": "w4014",
    "wName": "Workout XIV",
    "wtId": "wt0004",
    "wDifficulty": 4,
    "qIds": ["q03001", "q00004", "q00005", "q00002",
    "q03010", "q02002", "q02006", "q01010",
    "q03004", "q02007", "q01003", "q01011"]
  },
  {
    "wId": "w4015",
    "wName": "Workout XV",
    "wtId": "wt0004",
    "wDifficulty": 4,
    "qIds": ["q03002", "q00010", "q00008", "q00001",
    "q03008", "q02013", "q02009", "q01005",
    "q03005", "q02017", "q02001", "q01012"]
  },



  
  
  {
    "wId": "w4101",
    "wName": "Old Workout I",
    "wtId": "wt0004",
    "wDifficulty": 4,
    "qIds": ["q00008", "q00001", "q00004", "q00003",
    "q02005", "q00006", "q03006", "q01001", "q04001", "q02004", "q01004", "q03003"]
  },
  {
    "wId": "w4102",
    "wName": "Old Workout II",
    "wtId": "wt0004",
    "wDifficulty": 4,
    "qIds": ["q00005", "q00002", "q00004", "q00003",
    "q02008", "q00007", "q03004", "q01006", "q04003", "q02003", "q01005", "q03001"]
  },
  {
    "wId": "w4103",
    "wName": "Old Workout III",
    "wtId": "wt0004",
    "wDifficulty": 4,
    "qIds": ["q00008", "q00001", "q00004", "q00003",
    "q02007", "q00006", "q03008", "q01003", "q04001", "q02002", "q01007", "q03002"]
  },
  {
    "wId": "w4104",
    "wName": "Old Workout IV",
    "wtId": "wt0004",
    "wDifficulty": 4,
    "qIds": ["q00005", "q00002", "q00004", "q00003",
    "q02006", "q00007", "q03007", "q01002", "q04002", "q02001", "q01008", "q03005"]
  },
  {
    "wId": "w4105",
    "wName": "Old Workout V",
    "wtId": "wt0004",
    "wDifficulty": 4,
    "qIds": ["q00008", "q00001", "q00004", "q00006",
    "q02008", "q03003", "q02006", "q01007", "q02004", "q03005", "q02001", "q01003"]
  },
  {
    "wId": "w4106",
    "wName": "Old Workout VI",
    "wtId": "wt0004",
    "wDifficulty": 4,
    "qIds": ["q00005", "q00002", "q00003", "q00007",
    "q02007", "q03004", "q02005", "q01004", "q02004", "q03007", "q02002", "q01001"]
  },
  {
    "wId": "w4107",
    "wName": "Old Workout VII",
    "wtId": "wt0004",
    "wDifficulty": 4,
    "qIds": ["q00008", "q00001", "q00004", "q00006",
    "q02008", "q03002", "q02005", "q01005", "q02003", "q03008", "q02002", "q01006"]
  },
  {
    "wId": "w4108",
    "wName": "Old Workout VIII",
    "wtId": "wt0004",
    "wDifficulty": 4,
    "qIds": ["q00005", "q00002", "q00003", "q00007",
    "q02007", "q03001", "q02006", "q01002", "q02003", "q03006", "q02001", "q01008"]
  },
  {
    "wId": "w4109",
    "wName": "Old Workout IX",
    "wtId": "wt0004",
    "wDifficulty":4,
    "qIds": ["q00008", "q00001", "q00004", "q00003",
    "q04002", "q02001", "q01005", "q02004", "q01003", "q01002", "q01008", "q02007"]
  },
  {
    "wId": "w4110",
    "wName": "Old Workout X",
    "wtId": "wt0004",
    "wDifficulty": 4,
    "qIds": ["q00005", "q00002", "q00004", "q00003",
    "q04001", "q02002", "q01006", "q02005", "q01001", "q01004", "q02003", "q02006"]
  },
  {
    "wId": "w4111",
    "wName": "Old Workout XI",
    "wtId": "wt0004",
    "wDifficulty": 4,
    "qIds": ["q00005", "q00002", "q00004", "q00003",
    "q02002", "q01006", "q02005", "q02006", "q02001", "q01003", "q01008", "q02007"]
  },
  {
    "wId": "w4112",
    "wName": "Old Workout XII",
    "wtId": "wt0004",
    "wDifficulty": 4,
    "qIds": ["q00008", "q00001", "q00004", "q00003",
    "q04001", "q01001", "q02004", "q01002", "q04002", "q01004", "q02003", "q01005"]
  },




  {
    "wId": "w5001",
    "wName": "Workout I",
    "wtId": "wt0005",
    "wDifficulty": 5,
    "qIds": ["q00006", "q00004", "q00003", "q00011",
    "q04006", "q02004", "q02008", "q02007",
    "q02016", "q02003", "q01008", "q04002"]
  },
  {
    "wId": "w5002",
    "wName": "Workout II",
    "wtId": "wt0005",
    "wDifficulty": 5,
    "qIds": ["q00011", "q00007", "q00006", "q00009",
    "q04012", "q01016", "q04008", "q01007",
    "q01006", "q04006", "q01015", "q04004"]
  },
  {
    "wId": "w5003",
    "wName": "Workout III",
    "wtId": "wt0005",
    "wDifficulty": 5,
    "qIds": ["q00004", "q00008", "q00010", "q00005",
    "q04011", "q01013", "q04002", "q02009",
    "q02006", "q04014", "q02005", "q04010"]
  },
  {
    "wId": "w5004",
    "wName": "Workout IV",
    "wtId": "wt0005",
    "wDifficulty": 5,
    "qIds": ["q00012", "q00002", "q00003", "q00001",
    "q04001", "q01010", "q04013", "q01011",
    "q01012", "q04002", "q01005", "q04009"]
  },
  {
    "wId": "w5005",
    "wName": "Workout V",
    "wtId": "wt0005",
    "wDifficulty": 5,
    "qIds": ["q00010", "q00003", "q00011", "q00012",
    "q04007", "q01004", "q04014", "q03008",
    "q03010", "q04008", "q02014", "q04013"]
  },
  {
    "wId": "w5006",
    "wName": "Workout VI",
    "wtId": "wt0005",
    "wDifficulty": 5,
    "qIds": ["q00004", "q00006", "q00012", "q00010",
    "q04014", "q02016", "q02007", "q02008",
    "q02004", "q02017", "q02015", "q04008"]
  },
  {
    "wId": "w5007",
    "wName": "Workout VII",
    "wtId": "wt0005",
    "wDifficulty": 5,
    "qIds": ["q00009", "q03001", "q00007", "q03002",
    "q04012", "q03004", "q03006", "q04005",
    "q03007", "q04003", "q03005", "q04004"]
  },





  {
    "wId": "w5101",
    "wName": "OLD Workout I",
    "wtId": "wt0005",
    "wDifficulty": 5,
    "qIds": ["q00008", "q00001", "q00004", "q00006",
    "q04008", "q03001", "q02004", "q01007", "q04001", "q01001", "q03006", "q02005"]
  },
  {
    "wId": "w5102",
    "wName": "OLD Workout II",
    "wtId": "wt0005",
    "wDifficulty": 5,
    "qIds": ["q00005", "q00002", "q00003", "q00007",
    "q04007", "q03004", "q01003", "q01006", "q04003", "q02002", "q03005", "q02006"]
  },
  {
    "wId": "w5103",
    "wName": "OLD Workout III",
    "wtId": "wt0005",
    "wDifficulty": 5,
    "qIds": ["q00008", "q00001", "q00004", "q00006",
    "q04006", "q03003", "q01008", "q01005", "q04002", "q02001", "q03008", "q02007"]
  },
  {
    "wId": "w5104",
    "wName": "OLD Workout IV",
    "wtId": "wt0005",
    "wDifficulty": 5,
    "qIds": ["q00005", "q00002", "q00003", "q00007",
    "q04005", "q03002", "q02003", "q01004", "q04004", "q01002", "q03007", "q02008"]
  }
]